ovomaltino/__init__.py
ovomaltino/ovomaltino.py
ovomaltino/classes/__init__.py
ovomaltino/classes/agent.py
ovomaltino/classes/collective_conscience.py
ovomaltino/classes/education.py
ovomaltino/classes/family.py
ovomaltino/classes/groups.py
ovomaltino/classes/religion.py
ovomaltino/classes/social_fact.py
ovomaltino/database/__init__.py
ovomaltino/database/database.py
ovomaltino/datatype/__init__.py
ovomaltino/datatype/agent_memory_type.py
ovomaltino/datatype/agent_type.py
ovomaltino/datatype/group_type.py
ovomaltino/datatype/response_type.py
ovomaltino/datatype/sanction_type.py
ovomaltino/datatype/social_fact_moral_type.py
ovomaltino/datatype/social_fact_type.py
ovomaltino/handler/__init__.py
ovomaltino/handler/agent_handler.py
ovomaltino/handler/group_handler.py
ovomaltino/handler/mappers.py
ovomaltino/handler/ovomaltino_handler.py
ovomaltino/utils/__init__.py
ovomaltino/utils/influence_type.py
ovomaltino/utils/list_functions.py
Ovomaltino-0.0.15.dist-info/LICENSE
Ovomaltino-0.0.15.dist-info/METADATA
Ovomaltino-0.0.15.dist-info/WHEEL
Ovomaltino-0.0.15.dist-info/top_level.txt
Ovomaltino-0.0.15.dist-info/RECORD
