Metadata-Version: 2.1
Name: Ovomaltino
Version: 0.0.15
Summary: Multi agent system using social theories
Home-page: https://github.com/Ovomaltino/Ovomaltino
Author: Matheus Nobre Gomes
Author-email: matt-gomes@live.com
License: GPLv3+
Keywords: Ovomaltino
Classifier: Programming Language :: Python :: 3
Classifier: License :: OSI Approved :: GNU General Public License v3 or later (GPLv3+)
Classifier: Operating System :: OS Independent
License-File: LICENSE
Requires-Dist: numpy
Requires-Dist: pandas
Requires-Dist: requests
